README.rst
setup.cfg
setup.py
tangier_api/__init__.py
tangier_api/exceptions.py
tangier_api/helpers.py
tangier_api/settings.py
tangier_api/tests.py
tangier_api/wrappers.py
tangier_api.egg-info/PKG-INFO
tangier_api.egg-info/SOURCES.txt
tangier_api.egg-info/dependency_links.txt
tangier_api.egg-info/requires.txt
tangier_api.egg-info/top_level.txt
tangier_api/api/__init__.py
tangier_api/api/location.py
tangier_api/api/provider.py
tangier_api/api/schedule.py
tangier_api/api/specialty.py