Metadata-Version: 1.2
Name: tangier-api
Version: 1.2.1.dev0
Summary: A simple Python package to facilitate interactions with Tangier's API
Home-page: https://github.com/jjorissen52/tangier_api
Author: John-Paul Jorissen
Author-email: jjorissen52@gmail.com
License: Apache
Keywords: Tangier Python WebServices SOAP API
Platform: UNKNOWN
Classifier: Development Status :: 3 - Alpha
Classifier: Intended Audience :: Developers
Classifier: Programming Language :: Python :: 3.6
Classifier: Operating System :: Microsoft :: Windows :: Windows 10
Classifier: Operating System :: POSIX :: Linux
Classifier: Topic :: Office/Business
Classifier: License :: OSI Approved :: Apache Software License
Classifier: Programming Language :: Python :: 3.6
Requires-Python: >=3.6
